pytorch/__init__.py
pytorch/recipes/__init__.py
pytorch/recipes/version.py
pytorch/recipes/audio/__init__.py
pytorch/recipes/core/__init__.py
pytorch/recipes/core/base_train_app.py
pytorch/recipes/core/task_base.py
pytorch/recipes/core/conf/__init__.py
pytorch/recipes/core/conf/base_config.py
pytorch/recipes/core/conf/datamodule/random_data.yaml
pytorch/recipes/core/conf/fbl_resource_requirements/default.yaml
pytorch/recipes/core/conf/lr_scheduler/cosine_with_warmup.yaml
pytorch/recipes/core/conf/lr_scheduler/exponential.yaml
pytorch/recipes/core/conf/lr_scheduler/multi_step.yaml
pytorch/recipes/core/conf/lr_scheduler/step.yaml
pytorch/recipes/core/conf/module/loss/cross_entropy.yaml
pytorch/recipes/core/conf/module/lr_scheduler/step_lr.yaml
pytorch/recipes/core/conf/module/model/linear_dummy.yaml
pytorch/recipes/core/conf/module/optim/adam.yaml
pytorch/recipes/core/conf/module/optim/adamw.yaml
pytorch/recipes/core/conf/module/optim/sgd.yaml
pytorch/recipes/core/conf/optim/adamw.yaml
pytorch/recipes/core/conf/optim/sgd.yaml
pytorch/recipes/core/conf/trainer/cpu.yaml
pytorch/recipes/core/conf/trainer/multi_gpu.yaml
pytorch/recipes/core/conf/trainer/single_gpu.yaml
pytorch/recipes/graph/torchgraph/conf/datamodule/citeseer.yaml
pytorch/recipes/graph/torchgraph/conf/datamodule/cora.yaml
pytorch/recipes/graph/torchgraph/conf/datamodule/cora_full.yaml
pytorch/recipes/graph/torchgraph/conf/datamodule/pubmed.yaml
pytorch/recipes/graph/torchgraph/conf/module/loss/multiclass.yaml
pytorch/recipes/graph/torchgraph/conf/module/metrics/accuracy.yaml
pytorch/recipes/graph/torchgraph/conf/module/model/gcn.yaml
pytorch/recipes/graph/torchgraph/conf/module/model/gin.yaml
pytorch/recipes/launcher/__init__.py
pytorch/recipes/launcher/run.py
pytorch/recipes/multimodal/__init__.py
pytorch/recipes/multimodal/multimodal_train_app.py
pytorch/recipes/multimodal/utils.py
pytorch/recipes/multimodal/conf/__init__.py
pytorch/recipes/multimodal/conf/module/classifier/test_classifier.yaml
torchrecipes-0.1.0.dev2.dist-info/LICENCE
torchrecipes-0.1.0.dev2.dist-info/METADATA
torchrecipes-0.1.0.dev2.dist-info/WHEEL
torchrecipes-0.1.0.dev2.dist-info/top_level.txt
torchrecipes-0.1.0.dev2.dist-info/RECORD
