Metadata-Version: 2.1
Name: torchrecipes
Version: 0.1.0.dev2
Summary: Prototype of training recipes for PyTorch
Home-page: https://github.com/facebookexternal/stl_tasks
Author: PyTorch Ecosystem Foundations Team
Author-email: luispe@fb.com
License: BSD-3
Keywords: pytorch,machine learning
Platform: UNKNOWN
Classifier: Development Status :: 4 - Beta
Classifier: Intended Audience :: Developers
Classifier: Intended Audience :: Science/Research
Classifier: License :: OSI Approved :: BSD License
Classifier: Programming Language :: Python :: 3
Classifier: Programming Language :: Python :: 3.8
Classifier: Topic :: Scientific/Engineering :: Artificial Intelligence
Requires-Python: >=3.8
License-File: LICENCE
Requires-Dist: pyre-extensions
Provides-Extra: dev
Requires-Dist: pyre-extensions (>=0.0.21) ; extra == 'dev'
Requires-Dist: black (>=21.5b1) ; extra == 'dev'
Requires-Dist: pytorch-lightning (>=0.5.3) ; extra == 'dev'
Requires-Dist: torch (>=1.9.0) ; extra == 'dev'
Requires-Dist: torchvision (>=0.10.0) ; extra == 'dev'
Requires-Dist: importlib-metadata ; extra == 'dev'
